{"hash":"c8bcd6ad8391b569df9c1a96df3835b3bd2708bc","data":{"taggedBlogs":{"id":"3D Body Models","belongsTo":{"edges":[{"node":{"__typename":"blogPost","id":"2aadb6f2fb5ccc029f658450fe943d33","title":"Getting Started with OpenPose & SMPLify-X","date":"2020-08-07T00:00:00.000Z","path":"/blog/getting-started-with-open-pose-and-smp-lify-x/","excerpt":"A quick guide on how to set up and use the SMPLify-X container I've put together.","part":0,"cover":"https://raw.githubusercontent.com/vchoutas/smplify-x/master/images/teaser_fig.png","collection":null,"tags":[{"id":"3D Body Models","path":"/tags/3-d-body-models/"},{"id":"SMPLify-X","path":"/tags/smp-lify-x/"},{"id":"OpenPose","path":"/tags/open-pose/"},{"id":"Docker","path":"/tags/docker/"},{"id":"Development Environment","path":"/tags/development-environment/"}]}}]}}},"context":{}}